{
  "time": "45 minutes",
  "title": "Synthetics Tests in a CI/CD Pipeline",
  "details": {
    "intro": {
      "courseData": "background.sh",
      "code": "foreground.sh",
      "text": "intro.md"
    },
    "steps": [
      {
        "text": "cicd-this-lab.md"
      },
      {
        "text": "canary.md"
      }
    ],
    "finish": {
      "text": "finish.md"
    },
    "assets": {
      "host01": [
        {
          "file": "docker-compose.yml",
          "target": "/root/docker-compose.yml.asset"
        },
        {
            "file": "drone-runner-exec.conf ",
            "target": "/root/drone-runner-exec.conf.asset"
        },
        {
            "file": "droneio.database.sqlite",
            "target": "/root/droneio.database.sqlite.asset"
        },
        {
            "file": "gogs.app.ini",
            "target": "/root/gogs.app.ini.asset"
        },
        {
            "file": "git-credentials",
            "target": "/root/git-credentials.asset"
        },
        {
            "file": "labuser.git.tgz",
            "target": "/root/lbauser.git.tgz.asset"
        },
        {
            "file": "seed.sql",
            "target": "/root/seed.sql.asset"
        }
      ]
    }
  },
  "environment": {
    "uilayout": "terminal",
    "showide": true,
    "uieditorpath": "/root",
    "showdashboard": true,
    "dashboards": [
      {
        "name": "Storedog",
        "port": 3000
      }
    ]
  },
  "backend": {
    "imageid": "datadog-base-v2",
    "reuseConnection": "false"
  }
}